ebird/api/requests/__init__.py
ebird/api/requests/checklists.py
ebird/api/requests/client.py
ebird/api/requests/constants.py
ebird/api/requests/hotspots.py
ebird/api/requests/observations.py
ebird/api/requests/regions.py
ebird/api/requests/species.py
ebird/api/requests/statistics.py
ebird/api/requests/taxonomy.py
ebird/api/requests/utils.py
ebird/api/requests/validation.py
ebird_api-4.0.0.dist-info/licenses/LICENSE.txt
ebird_api-4.0.0.dist-info/METADATA
ebird_api-4.0.0.dist-info/WHEEL
ebird_api-4.0.0.dist-info/top_level.txt
ebird_api-4.0.0.dist-info/RECORD
